tsapix/__init__.py
tsapix/dimvals.py
tsapix/envbase.py
tsapix/setup.py
tsapix/utils.py
tsapix/ibkr/qqq.py
tsapix/ibkr/test.py
tsapix/spider/__init__.py
tsapix/spider/base.py
tsapix/spider/eastmoney.py
tsapix/spider/shared.py
tsapix/spider/sina.py
tsapix/spider/sina_keyword_screening.py
tsapix/spider/ticker_cn_update.py
tsapix/spider/ticker_us_update.py
tsapix/spider/utils.py
tsapix/spider/version.py
tsapix/spider/webull_objectdetection_alert.py
tsapix/spider/webull_tickcollector.py
tsapix/tools/cn_plot.py
tsapix/tools/objectdetection.py
tsapix/tools/taskbase.py
tsapix/tools/us_intraday.py
tsapix-0.0.2.dist-info/licenses/LICENSE
tsapix-0.0.2.dist-info/METADATA
tsapix-0.0.2.dist-info/WHEEL
tsapix-0.0.2.dist-info/top_level.txt
tsapix-0.0.2.dist-info/RECORD
